Metadata-Version: 2.1
Name: folderdb
Version: 0.0.1.0
Summary: A directory-based database package
Author: OmgRod
License: MIT
